auto_rpa/__init__.py
auto_rpa/auto_window/__init__.py
auto_rpa/auto_window/actuator.py
auto_rpa/auto_window/base_action.py
auto_rpa/auto_window/client.py
auto_rpa/auto_window/init_config.py
auto_rpa/auto_window/main.py
auto_rpa/auto_window/simulate_operate.py
auto_rpa/utils/__init__.py
auto_rpa/utils/dd_sender.py
auto_rpa/utils/ftp_client.py
auto_rpa/utils/log_tools.py
auto_rpa/utils/pd_reader.py
auto_rpa/utils/ssh_tools.py
auto_rpa/utils/mysql_utils/__init__.py
auto_rpa/utils/mysql_utils/db_base.py
auto_rpa/utils/mysql_utils/db_con.py
auto_rpa/utils/mysql_utils/db_table.py
auto_rpa-0.1.54.dist-info/METADATA
auto_rpa-0.1.54.dist-info/WHEEL
auto_rpa-0.1.54.dist-info/top_level.txt
auto_rpa-0.1.54.dist-info/RECORD
