Metadata-Version: 2.1
Name: auto-rpa
Version: 0.1.54
Summary: auto
Home-page: https://github.com/spiderzzf/auto_rpa.git
Author: zzf
Author-email: 13051732531@163.com
License: MIT
Platform: UNKNOWN
Requires-Dist: pandas
Requires-Dist: requests
Requires-Dist: psutil
Requires-Dist: PyAutoGUI
Requires-Dist: pynput
Requires-Dist: pypiwin32
Requires-Dist: Pillow
Requires-Dist: pytesseract
Requires-Dist: PyMySQL
Requires-Dist: DBUtils
